cltrier_lib/__init__.py
cltrier_lib/classify/__init__.py
cltrier_lib/classify/schemas.py
cltrier_lib/inference/__init__.py
cltrier_lib/inference/schemas.py
cltrier_lib-0.1.8.dist-info/METADATA
cltrier_lib-0.1.8.dist-info/WHEEL
cltrier_lib-0.1.8.dist-info/RECORD
